CHANGELOG.md
README.md
cafram/__init__.py
cafram/base.py
cafram/nodes.py
cafram/utils.py
paasify/__init__.py
paasify/app.py
paasify/assets/collections/paasify/.gitignore
paasify/assets/collections/paasify/.paasify/docs/app_debug.md
paasify/assets/collections/paasify/.paasify/docs/app_dns.md
paasify/assets/collections/paasify/.paasify/docs/app_dummy.md
paasify/assets/collections/paasify/.paasify/docs/app_example.md
paasify/assets/collections/paasify/.paasify/docs/app_home.md
paasify/assets/collections/paasify/.paasify/docs/app_network.md
paasify/assets/collections/paasify/.paasify/docs/app_proxy.md
paasify/assets/collections/paasify/.paasify/docs/index.md
paasify/assets/collections/paasify/.paasify/docs/jsonnet_docker-debug.html
paasify/assets/collections/paasify/.paasify/docs/jsonnet_docker-debug.json
paasify/assets/collections/paasify/.paasify/docs/jsonnet_docker-debug.md
paasify/assets/collections/paasify/.paasify/docs/jsonnet_docker-net-attach.html
paasify/assets/collections/paasify/.paasify/docs/jsonnet_docker-net-attach.json
paasify/assets/collections/paasify/.paasify/docs/jsonnet_docker-net-attach.md
paasify/assets/collections/paasify/.paasify/docs/jsonnet_example.html
paasify/assets/collections/paasify/.paasify/docs/jsonnet_example.json
paasify/assets/collections/paasify/.paasify/docs/jsonnet_example.md
paasify/assets/collections/paasify/.paasify/docs/jsonnet_homepage.html
paasify/assets/collections/paasify/.paasify/docs/jsonnet_homepage.json
paasify/assets/collections/paasify/.paasify/docs/jsonnet_homepage.md
paasify/assets/collections/paasify/.paasify/docs/jsonnet_mysql-adminer.html
paasify/assets/collections/paasify/.paasify/docs/jsonnet_mysql-adminer.json
paasify/assets/collections/paasify/.paasify/docs/jsonnet_mysql-adminer.md
paasify/assets/collections/paasify/.paasify/docs/jsonnet_traefik-mw.html
paasify/assets/collections/paasify/.paasify/docs/jsonnet_traefik-mw.json
paasify/assets/collections/paasify/.paasify/docs/jsonnet_traefik-mw.md
paasify-0.1.2.dist-info/METADATA
paasify-0.1.2.dist-info/LICENSE.txt
paasify-0.1.2.dist-info/WHEEL
paasify-0.1.2.dist-info/entry_points.txt
paasify-0.1.2.dist-info/RECORD
