Metadata-Version: 2.1
Name: paasify
Version: 0.1.2
Summary: Paasify your docker-compose files
Home-page: https://github.com/barbu-it/paasify
License: Apache License
Keywords: paasify,docker,docker-compose,jsonnet
Author: MrJK
Requires-Python: >=3.8,<4.0
Classifier: Development Status :: 4 - Beta
Classifier: Environment :: Console
Classifier: Intended Audience :: Developers
Classifier: Intended Audience :: Information Technology
Classifier: Intended Audience :: System Administrators
Classifier: License :: OSI Approved
Classifier: License :: Other/Proprietary License
Classifier: Operating System :: OS Independent
Classifier: Programming Language :: Python :: 3
Classifier: Programming Language :: Python :: 3.8
Classifier: Programming Language :: Python :: 3.9
Classifier: Programming Language :: Python :: 3.10
Classifier: Programming Language :: Python :: 3.11
Classifier: Programming Language :: Python :: 3
Classifier: Topic :: Software Development
Classifier: Topic :: Utilities
Requires-Dist: anyconfig (>=0.13.0,<0.14.0)
Requires-Dist: giturlparse (>=0.10.0,<0.11.0)
Requires-Dist: json-schema-for-humans (>=0.44,<0.45)
Requires-Dist: jsonnet (>=0.19.1,<0.20.0)
Requires-Dist: jsonschema (>=4.17.0,<5.0.0)
Requires-Dist: pyaml (>=21.10.1,<22.0.0)
Requires-Dist: rich (>=13.3.1,<14.0.0)
Requires-Dist: ruamel-yaml (>=0.17.21,<0.18.0)
Requires-Dist: semver (>=2.13.0,<3.0.0)
Requires-Dist: sh (>=1.14.3,<2.0.0)
Requires-Dist: single-version (>=1.5.1,<2.0.0)
Requires-Dist: typer (>=0.7.0,<0.8.0)
Project-URL: Repository, https://github.com/barbu-it/paasify
